Metadata-Version: 1.0
Name: bootcampclass-distributions
Version: 1.0
Summary: Gaussian distributions
Home-page: UNKNOWN
Author: Uzoma Uzosike
Author-email: uzoma.uzosike@gmail.com
License: UNKNOWN
Platform: UNKNOWN
